{"options":{},"indexes":[{"v":1,"key":{"_id":1},"name":"_id_","ns":"myschoolbus.stops"},{"v":1,"key":{"meta.created.user":1.0},"name":"meta.created.user_1","ns":"myschoolbus.stops"},{"v":1,"key":{"route_id":1.0},"name":"route_id_1","ns":"myschoolbus.stops"},{"v":1,"key":{"name":1.0},"name":"name_1","ns":"myschoolbus.stops"},{"v":1,"key":{"_id":1.0,"meta.created.user":1.0},"name":"_id_1_meta.created.user_1","ns":"myschoolbus.stops"},{"v":1,"key":{"meta.created.user":1.0,"name":1.0},"name":"meta.created.user_1_name_1","ns":"myschoolbus.stops"},{"v":1,"key":{"meta.created.user":1.0,"route_id":1.0},"name":"meta.created.user_1_route_id_1","ns":"myschoolbus.stops"}]}